MANIFEST.in
README
setup.py
iPypr/__init__.py
iPypr/_iPypr.py
iPypr.egg-info/PKG-INFO
iPypr.egg-info/SOURCES.txt
iPypr.egg-info/dependency_links.txt
iPypr.egg-info/top_level.txt