Metadata-Version: 1.0
Name: iPypr
Version: 0.11
Summary: Like PHP print_r for Python
Home-page: http://c.isme.pub/Pypr
Author: Casstiel
Author-email: emo_ooppwwqq0@163.com
License: UNKNOWN
Platform: UNKNOWN
